a_pandas_ex_df_to_string/LICENSE
a_pandas_ex_df_to_string/README.MD
a_pandas_ex_df_to_string/__init__.py
a_pandas_ex_df_to_string/requirements.txt
a_pandas_ex_df_to_string/thirdparty.json
a_pandas_ex_df_to_string-0.14.dist-info/LICENSE.rst
a_pandas_ex_df_to_string-0.14.dist-info/METADATA
a_pandas_ex_df_to_string-0.14.dist-info/WHEEL
a_pandas_ex_df_to_string-0.14.dist-info/top_level.txt
a_pandas_ex_df_to_string-0.14.dist-info/RECORD
