Metadata-Version: 2.1
Name: a-pandas-ex-df-to-string
Version: 0.14
Summary: Just a function to convert everything in Pandas DataFrames / Series to string
Home-page: https://github.com/hansalemaos/a_pandas_ex_df_to_string
Author: Johannes Fischer
Author-email: aulasparticularesdealemaosp@gmail.com
License: MIT
Keywords: pandas,numpy,dataframe,series
Classifier: Development Status :: 4 - Beta
Classifier: Programming Language :: Python :: 3 :: Only
Classifier: Programming Language :: Python :: 3.10
Classifier: Topic :: Software Development :: Libraries :: Python Modules
Classifier: Topic :: Utilities
License-File: LICENSE.rst
Requires-Dist: pandas
